LICENSE
MANIFEST.in
README.rst
setup.cfg
setup.py
versioneer.py
tests/__init__.py
tests/test_general.py
tpRigToolkit/__init__.py
tpRigToolkit/tools/__init__.py
tpRigToolkit/tools/controlrig/__init__.py
tpRigToolkit/tools/controlrig/__logging__.ini
tpRigToolkit/tools/controlrig/__version__.py
tpRigToolkit/tools/controlrig/_version.py
tpRigToolkit/tools/controlrig/core/__init__.py
tpRigToolkit/tools/controlrig/core/client.py
tpRigToolkit/tools/controlrig/core/consts.py
tpRigToolkit/tools/controlrig/core/controldata.py
tpRigToolkit/tools/controlrig/core/controller.py
tpRigToolkit/tools/controlrig/core/model.py
tpRigToolkit/tools/controlrig/core/tool.py
tpRigToolkit/tools/controlrig/core/toolset.py
tpRigToolkit/tools/controlrig/core/view.py
tpRigToolkit/tools/controlrig/data/controls_data.json
tpRigToolkit/tools/controlrig/dccs/__init__.py
tpRigToolkit/tools/controlrig/dccs/max/__init__.py
tpRigToolkit/tools/controlrig/dccs/max/server.py
tpRigToolkit/tools/controlrig/dccs/maya/__init__.py
tpRigToolkit/tools/controlrig/dccs/maya/server.py
tpRigToolkit/tools/controlrig/resources/icons/color/camera.png
tpRigToolkit/tools/controlrig/resources/icons/color/delete.png
tpRigToolkit/tools/controlrig/widgets/__init__.py
tpRigToolkit/tools/controlrig/widgets/controlcapturer.py
tpRigToolkit/tools/controlrig/widgets/controlslist.py
tpRigToolkit/tools/controlrig/widgets/controlutils.py
tpRigToolkit/tools/controlrig/widgets/controlviewer.py
tpRigToolkit_tools_controlrig.egg-info/PKG-INFO
tpRigToolkit_tools_controlrig.egg-info/SOURCES.txt
tpRigToolkit_tools_controlrig.egg-info/dependency_links.txt
tpRigToolkit_tools_controlrig.egg-info/not-zip-safe
tpRigToolkit_tools_controlrig.egg-info/requires.txt
tpRigToolkit_tools_controlrig.egg-info/top_level.txt