Metadata-Version: 2.1
Name: tpRigToolkit-tools-controlrig
Version: 0.0.3
Summary: Tool to create rig curve based controls
Home-page: https://github.com/tpRigToolkit/tpRigToolkit-tools-controlrig
Author: Tomas Poveda
Author-email: tpovedatd@gmail.com
License: MIT
Platform: UNKNOWN
Provides-Extra: dev
Provides-Extra: test
